yks.py
yks-0.0.9.dist-info/LICENSE
yks-0.0.9.dist-info/METADATA
yks-0.0.9.dist-info/WHEEL
yks-0.0.9.dist-info/entry_points.txt
yks-0.0.9.dist-info/top_level.txt
yks-0.0.9.dist-info/RECORD
