Metadata-Version: 2.1
Name: yks
Version: 0.0.9
Summary: A sample project
Home-page: https://github.com/tonikarppi/yks
Author: Toni Karppi
Author-email: karppitoni@gmail.com
License: UNKNOWN
Keywords: sample
Platform: UNKNOWN
Classifier: Programming Language :: Python :: 3
Classifier: License :: OSI Approved :: MIT License
Classifier: Operating System :: OS Independent
Requires-Python: >=3.6
